MonoTools/__init__.py
MonoTools/fit.py
MonoTools/lightcurve.py
MonoTools/search.py
MonoTools/search_old.py
MonoTools/tools.py
MonoTools/data/tables/BolMag_interpolations.models
MonoTools/data/tables/Cheops_Quad_LDs.txt
MonoTools/data/tables/Cheops_Quad_LDs_AllFeHs.txt
MonoTools/data/tables/GKSPCPapTable1_Final.txt.gz
MonoTools/data/tables/GKSPCPapTable2_Final.txt.gz
MonoTools/data/tables/KeplerLDlaws.txt
MonoTools/data/tables/LogMePriorFromRe.txt
MonoTools/data/tables/all_bernmodel_both.npy.gz
MonoTools/data/tables/emarg_array_flat.txt.gz
MonoTools/data/tables/emarg_array_kip.txt.gz
MonoTools/data/tables/emarg_array_vve.txt.gz
MonoTools/data/tables/logprob_array_flat.txt.gz
MonoTools/data/tables/logprob_array_kip.txt.gz
MonoTools/data/tables/logprob_array_vve.txt.gz
MonoTools/data/tables/maxecc_axis_0.txt
MonoTools/data/tables/relvels_axis_1.txt
MonoTools/data/tables/tces_per_cadence.txt.gz
MonoTools/data/tables/tessLDs.txt
MonoTools/data/tables/tess_lc_locations.csv
MonoTools/tests/test_fit.py
monotools-1.0.0.dist-info/licenses/LICENSE
monotools-1.0.0.dist-info/METADATA
monotools-1.0.0.dist-info/WHEEL
monotools-1.0.0.dist-info/top_level.txt
monotools-1.0.0.dist-info/RECORD
