Metadata-Version: 2.4
Name: MonoTools
Version: 1.0.0
Summary: A package for detecting, vetting and modelling transiting exoplanets on uncertain periods
Home-page: https://github.com/hposborn/MonoTools
Author: Hugh P. Osborn
Author-email: hugh.osborn@space.unibe.ch
License: BSD 2-clause
Project-URL: Bug Tracker, https://github.com/hposborn/MonoTools/issues
Classifier: Development Status :: 1 - Planning
Classifier: Intended Audience :: Science/Research
License-File: LICENSE
Requires-Dist: matplotlib
Requires-Dist: numpy
Requires-Dist: pandas
Requires-Dist: scipy==1.12
Requires-Dist: astropy
Requires-Dist: astroquery
Requires-Dist: batman-package
Requires-Dist: lightkurve==1.11.0
Requires-Dist: arviz
Requires-Dist: pymc
Requires-Dist: pymc_ext
Requires-Dist: exoplanet[pymc]
Requires-Dist: celerite2
Requires-Dist: requests
Requires-Dist: urllib3
Requires-Dist: lxml
Requires-Dist: httplib2
Requires-Dist: h5py
Requires-Dist: bokeh
Requires-Dist: corner
Requires-Dist: transitleastsquares
Requires-Dist: seaborn
Requires-Dist: iteround
Requires-Dist: sphinx==4.3.1
Requires-Dist: nbsphinx
Requires-Dist: myst_parser
Requires-Dist: sphinx_rtd_theme
Requires-Dist: netcdf4
Requires-Dist: openpyxl
Dynamic: author
Dynamic: author-email
Dynamic: classifier
Dynamic: description
Dynamic: description-content-type
Dynamic: home-page
Dynamic: license
Dynamic: license-file
Dynamic: project-url
Dynamic: requires-dist
Dynamic: summary
